viggoorg/__init__.py
viggoorg/resources.py
viggoorg/subsystem/__init__.py
viggoorg/subsystem/sysadmin/__init__.py
viggoorg/subsystem/sysadmin/domain_org/__init__.py
viggoorg/subsystem/sysadmin/domain_org/resource.py
viggoorg-1.0.1.dist-info/AUTHORS
viggoorg-1.0.1.dist-info/METADATA
viggoorg-1.0.1.dist-info/WHEEL
viggoorg-1.0.1.dist-info/top_level.txt
viggoorg-1.0.1.dist-info/RECORD
